lve/__init__.py
lve/errors.py
lve/hooks.py
lve/inference.py
lve/lve.py
lve/model_store.py
lve/prompt.py
lve/repo.py
lve/version.py
lve/checkers/__init__.py
lve/checkers/base.py
lve/checkers/bias.py
lve/checkers/consistency.py
lve/checkers/match.py
lve/checkers/pii.py
lve/checkers/toxicity.py
lve/cli/__init__.py
lve/cli/cli.py
lve/cli/commit.py
lve/cli/pr.py
lve/cli/prepare.py
lve/cli/readme.py
lve/cli/record.py
lve/cli/run.py
lve/cli/show.py
lve/cli/status.py
lve/cli/termutils.py
lve/cli/unit_test.py
lve/tests/__init__.py
lve/tests/test_checkers.py
lve/tests/test_inference.py
lve/tests/test_lve.py
lve/tests/test_repository.py
lve/utils/__init__.py
lve/utils/importutils.py
lve_tools-0.1.4.dist-info/METADATA
lve_tools-0.1.4.dist-info/WHEEL
lve_tools-0.1.4.dist-info/entry_points.txt
lve_tools-0.1.4.dist-info/top_level.txt
lve_tools-0.1.4.dist-info/RECORD
