Metadata-Version: 2.1
Name: lve-tools
Version: 0.1.4
Summary: Tools for documenting and recording language model vulnerabilities and exposures.
Author: LVE Team
Requires-Python: >=3.10
Requires-Dist: openai
Requires-Dist: replicate
Requires-Dist: pydantic
Requires-Dist: questionary
Requires-Dist: termcolor
Requires-Dist: GitPython
Requires-Dist: lmql >=0.7.1
